auldcommons/__init__.py
auldcommons/types/trees/__init__.py
auldcommons/types/trees/_aulddict.py
auldcommons/types/trees/old_aulddict.py
auldcommons-0.0.1.dist-info/LICENSE
auldcommons-0.0.1.dist-info/METADATA
auldcommons-0.0.1.dist-info/WHEEL
auldcommons-0.0.1.dist-info/top_level.txt
auldcommons-0.0.1.dist-info/RECORD
